VERSION
fibkvc/__init__.py
fibkvc/fibonacci_cache.py
fibkvc/fibonacci_config.py
fibkvc/fibonacci_hash.py
fibkvc-0.1.3.dist-info/licenses/LICENSE
fibkvc-0.1.3.dist-info/METADATA
fibkvc-0.1.3.dist-info/WHEEL
fibkvc-0.1.3.dist-info/top_level.txt
fibkvc-0.1.3.dist-info/RECORD
