Metadata-Version: 2.4
Name: fibkvc
Version: 0.1.3
Summary: High-performance KV cache optimization using Fibonacci hashing for LLM deployment
Home-page: https://github.com/calivision/fibkvc
Author: David Anderson
Author-email: danders3@iit.edu
Project-URL: Bug Tracker, https://github.com/calivision/fibkvc/issues
Project-URL: Documentation, https://fibkvc.readthedocs.io
Project-URL: Source Code, https://github.com/calivision/fibkvc
Project-URL: Paper, https://arxiv.org/abs/2601.xxxxx
Keywords: fibonacci hashing kv-cache llm diffusion-models optimization performance
Classifier: Development Status :: 4 - Beta
Classifier: Intended Audience :: Developers
Classifier: Intended Audience :: Science/Research
Classifier: License :: OSI Approved :: MIT License
Classifier: Operating System :: OS Independent
Classifier: Programming Language :: Python :: 3
Classifier: Programming Language :: Python :: 3.8
Classifier: Programming Language :: Python :: 3.9
Classifier: Programming Language :: Python :: 3.10
Classifier: Programming Language :: Python :: 3.11
Classifier: Topic :: Scientific/Engineering :: Artificial Intelligence
Classifier: Topic :: Software Development :: Libraries :: Python Modules
Requires-Python: >=3.8
License-File: LICENSE
Provides-Extra: dev
Requires-Dist: pytest>=7.0.0; extra == "dev"
Requires-Dist: pytest-cov>=4.0.0; extra == "dev"
Requires-Dist: hypothesis>=6.0.0; extra == "dev"
Requires-Dist: black>=22.0.0; extra == "dev"
Requires-Dist: flake8>=5.0.0; extra == "dev"
Requires-Dist: mypy>=0.990; extra == "dev"
Requires-Dist: isort>=5.10.0; extra == "dev"
Dynamic: author
Dynamic: author-email
Dynamic: classifier
Dynamic: description
Dynamic: description-content-type
Dynamic: home-page
Dynamic: keywords
Dynamic: license-file
Dynamic: project-url
Dynamic: provides-extra
Dynamic: requires-python
Dynamic: summary
